pysecuritytrails/__init__.py
pysecuritytrails/api.py
pysecuritytrails/cli.py
pysecuritytrails-0.1.3.dist-info/LICENSE
pysecuritytrails-0.1.3.dist-info/METADATA
pysecuritytrails-0.1.3.dist-info/WHEEL
pysecuritytrails-0.1.3.dist-info/entry_points.txt
pysecuritytrails-0.1.3.dist-info/top_level.txt
pysecuritytrails-0.1.3.dist-info/RECORD
