Metadata-Version: 2.1
Name: pysecuritytrails
Version: 0.1.3
Summary: Python wrapper around the Security Trails API
Home-page: https://github.com/Te-k/pysecuritytrails
Author: Tek
Author-email: tek@randhome.io
License: GPLv3
Keywords: security
Platform: UNKNOWN
Classifier: Programming Language :: Python :: 3
Classifier: License :: OSI Approved :: GNU General Public License v3 (GPLv3)
Classifier: Operating System :: OS Independent
Requires-Python: >=3.5
Requires-Dist: requests
Requires-Dist: configparser
